setup.cfg
setup.py
automata/__init__.py
automata/language.py
automata/testing.py
automata/data_structures/Stack.py
automata/data_structures/__init__.py
automata/fa/DFA.py
automata/fa/Mealy.py
automata/fa/Moore.py
automata/fa/NDFA.py
automata/fa/__init__.py
automata_python.egg-info/PKG-INFO
automata_python.egg-info/SOURCES.txt
automata_python.egg-info/dependency_links.txt
automata_python.egg-info/top_level.txt