Metadata-Version: 1.0
Name: automata-python
Version: 0.0.5
Summary: Python Automata Library
Home-page: https://github.com/hemangsk/automata-python
Author: Hemang Kumar
Author-email: hemangsk@gmail.com
License: GPLv3
Keywords: language finite automata turing machine push down automata linear bound automata
Platform: UNKNOWN
